py_bdd_test/__init__.py
py_bdd_test/list_steps.py
py_bdd_test/features/__init__.py
py_bdd_test/features/steps/__init__.py
py_bdd_test/features/steps/bdd_config.py
py_bdd_test/features/steps/http_steps.py
py_bdd_test/features/steps/json_steps.py
py_bdd_test/features/steps/kafka_steps.py
py_bdd_test/features/steps/ui_steps.py
py_bdd_test/features/steps/utils.py
py_bdd_test-1.0.30.dist-info/METADATA
py_bdd_test-1.0.30.dist-info/WHEEL
py_bdd_test-1.0.30.dist-info/entry_points.txt
py_bdd_test-1.0.30.dist-info/top_level.txt
py_bdd_test-1.0.30.dist-info/RECORD
