Metadata-Version: 2.2
Name: py-bdd-test
Version: 1.0.30
Requires-Python: >=3.7
Requires-Dist: behave
Requires-Dist: kafka-python
Requires-Dist: parse
Requires-Dist: parse_type
Requires-Dist: pyhamcrest
Requires-Dist: requests
Requires-Dist: PyHamcrest
Requires-Dist: pyyaml
Requires-Dist: python-multipart
Requires-Dist: typing
Requires-Dist: python-dotenv
Requires-Dist: playwright
Requires-Dist: kafka-python
Dynamic: requires-dist
Dynamic: requires-python
